[
    {
        "accountId": "16SpacegeUTft9v3ts27CEC3tJaxgvE4uZeCctThFH3Vb24p",
        "identity": {
            "display": "Staker Space",
            "legal": "",
            "web": "https://staker.space",
            "riot": "@gnossienli:matrix.org",
            "email": "hello@staker.space",
            "pgpFingerprint": "",
            "image": "",
            "twitter": "@StakerSpace"
        },
        "staked": 10000000495009,
        "commission": "3%"
    },
    {
        "accountId": "16HvKyV9B61hsop3ZY6pWYeV537S29kd9pb9FMrPzx49ym5X",
        "identity": {
            "display": "TheGuild",
            "legal": "",
            "web": "",
            "riot": "",
            "email": "theguildsource@gmail.com",
            "pgpFingerprint": "",
            "image": "",
            "twitter": ""
        },
        "staked": 53573567154660,
        "commission": "3%"
    },
    {
        "accountId": "12713bbq45c66CN9AD7yusSXWE1kY91DcMpjVcB2rXqZKy2w",
        "identity": {
            "display": "🔒stateless_money🔒",
            "legal": "",
            "web": "https://www.stateless.money/",
            "riot": "@aaronschwarz:matrix.org",
            "email": "Aaron.Antonopoulos@pm.me",
            "pgpFingerprint": "",
            "image": "",
            "twitter": "@MoneyStateless"
        },
        "staked": 2567306085408,
        "commission": "5%"
    },
    {
        "accountId": "1MrurrNb4VTrRJUXT6fGxHFdmwwscqHZUFkMistMsP8k5Nk",
        "identity": {
            "display": "🛡 DWELLIR DOT 🛡",
            "legal": "",
            "web": "https://dwellir.com",
            "riot": "@dwellir:matrix.org",
            "email": "info@dwellir.com",
            "pgpFingerprint": "",
            "image": "",
            "twitter": "@DwellirOfficial"
        },
        "staked": 56443720762506,
        "commission": "3%"
    },
    {
        "accountId": "15fU523Wq5BCt2NWAmrCU6p8nFB29uVifeG7bwYJHbw5Mmd9",
        "identity": {
            "display": "SNZPool-1",
            "legal": "SNZPool",
            "web": "https://snzholding.com",
            "riot": "",
            "email": "hi@snzholding.com",
            "pgpFingerprint": "",
            "image": "",
            "twitter": "@snzholding"
        },
        "staked": 10000000000,
        "commission": "1%"
    },
    {
        "accountId": "13dVcF8BjzUpYujj5HxumDLPwpHzMPwzPZAZHJQEbKRJuNgT",
        "identity": {
            "display": "T-Systems MMS",
            "legal": "T-Systems MMS",
            "web": "",
            "riot": "",
            "email": "staking@t-systems-mms.com",
            "pgpFingerprint": "",
            "image": "",
            "twitter": "@TSystems_MMS"
        },
        "staked": 10000000000,
        "commission": "10%"
    },
    {
        "accountId": "155Uc2YERq1vYYcS2owKa3vZk2zyehP624JzX5frkJkPY7db",
        "identity": {
            "display": "STAKINGDX_COM",
            "legal": "STAKINGDX_COM",
            "web": "https://stakingdx.com",
            "riot": "@stakingdx:matrix.org",
            "email": "info@stakingdx.com",
            "pgpFingerprint": "",
            "image": "",
            "twitter": "@StakingDx"
        },
        "staked": 50951641296190,
        "commission": "3%"
    },
    {
        "accountId": "12dvyqCFhVubTDqMdojyjhkxVUMaYVXWLv8uZW1NomUunPmN",
        "identity": {
            "display": "Nodeasy",
            "legal": "",
            "web": "",
            "riot": "@crabbean:matrix.org",
            "email": "wenzhihao@bitopia.cn",
            "pgpFingerprint": "",
            "image": "",
            "twitter": "@Nodeasy"
        },
        "staked": 100011669089850,
        "commission": "3%"
    },
    {
        "accountId": "1cFsLn7o74nmjbRyDtMAnMpQMc5ZLsjgCSz9Np2mcejUK83",
        "identity": {
            "display": "Uno Staking",
            "legal": "",
            "web": "",
            "riot": "@unostaking:matrix.org",
            "email": "operator@unostaking.com",
            "pgpFingerprint": "",
            "image": "",
            "twitter": "@UnoStaking"
        },
        "staked": 106426099142650,
        "commission": "3%"
    },
    {
        "accountId": "148HzdSuFsDrNKnAHFs81BJzZxmKgwEC6Pmpw2QJnTy3Hv3R",
        "identity": {
            "display": "CoinFund/Grassfed",
            "legal": "",
            "web": "",
            "riot": "",
            "email": "",
            "pgpFingerprint": "",
            "image": "",
            "twitter": "@coinfund_io"
        },
        "staked": 124308957065326,
        "commission": "5%"
    },
    {
        "accountId": "15kkg1mK1tCGgqqo3c1CghtKCQsBEAPPjYNNmmRT3r29FeRX",
        "identity": {
            "display": "ANAMIX",
            "legal": "ANAMIX",
            "web": "https://anamix.top/",
            "riot": "@dbpatty:matrix.org",
            "email": "anamix@polkadot.pro",
            "pgpFingerprint": "",
            "image": "",
            "twitter": ""
        },
        "staked": 105874082791514,
        "commission": "3%"
    },
    {
        "accountId": "15iwm1HrcGiTZoZenijMTCayRD3hM2RpKde3LrrNxPKAMjTg",
        "identity": {
            "display": "UBIK CAPITAL",
            "legal": "",
            "web": "",
            "riot": "",
            "email": "contact@ubik.capital",
            "pgpFingerprint": "",
            "image": "",
            "twitter": "@ubikcapital"
        },
        "staked": 56093231245646,
        "commission": "2.98%"
    },
    {
        "accountId": "13rkfSaFsMEFJAV1wcQcnbJnxiigJTb78qkkLSEvUNPA2QVZ",
        "identity": {
            "display": "XUAN",
            "legal": "XUAN",
            "web": "",
            "riot": "@xuan93:matrix.org",
            "email": "yangjingxuanmail@gmail.com",
            "pgpFingerprint": "",
            "image": "",
            "twitter": ""
        },
        "staked": 50001421622738,
        "commission": "3%"
    },
    {
        "accountId": "1653t723BHhC2krGCFKUUNDQb5sUafy5pZvKVwnwo1oMAMi7",
        "identity": {
            "display": "Staked",
            "legal": "",
            "web": "https://staked.us",
            "riot": "",
            "email": "sales@staked.us",
            "pgpFingerprint": "",
            "image": "",
            "twitter": "@staked_us"
        },
        "staked": 10004538308,
        "commission": "10%"
    },
    {
        "accountId": "14Y4s6V1PWrwBLvxW47gcYgZCGTYekmmzvFsK1kiqNH2d84t",
        "identity": {
            "display": "RockX_Polkadot",
            "legal": "RockX",
            "web": "https://www.rockx.com",
            "riot": "",
            "email": "support@rockx.com",
            "pgpFingerprint": "",
            "image": "",
            "twitter": "@rockx_official"
        },
        "staked": 22157724174367,
        "commission": "10%"
    },
    {
        "accountId": "1WG3jyNqniQMRZGQUc7QD2kVLT8hkRPGMSqAb5XYQM1UDxN",
        "identity": {
            "display": "DokiaCapital",
            "legal": "",
            "web": "https://staking.dokia.cloud",
            "riot": "@awrelll:matrix.org",
            "email": "",
            "pgpFingerprint": "",
            "image": "",
            "twitter": ""
        },
        "staked": 6044401583000000,
        "commission": "5%"
    }
]